txt2sql/data/dataloaders.py
txt2sql/data/datasets.py
txt2sql/data/utils/download.py
txt2sql/data/utils/schema_to_text.py
txt2sql/data/utils/sqlite_functions.py
txt2sql/metrics/__init__.py
txt2sql/metrics/essence_match.py
txt2sql/metrics/execution_match.py
txt2sql/metrics/intent_match.py
txt2sql/metrics/soft_f1.py
txt2sql/metrics/sql_match.py
txt2sql/metrics/utils.py
txt2sql-0.4.0.dist-info/licenses/LICENSE
txt2sql-0.4.0.dist-info/METADATA
txt2sql-0.4.0.dist-info/WHEEL
txt2sql-0.4.0.dist-info/top_level.txt
txt2sql-0.4.0.dist-info/RECORD
