Metadata-Version: 2.4
Name: txt2sql
Version: 0.4.0
Summary: An open source package for all your txt2sql needs.
Author-email: Unso Jo <unso@gena.co>
License: MIT License
Classifier: Programming Language :: Python :: 3
Classifier: Programming Language :: Python :: 3.7
Classifier: License :: OSI Approved :: MIT License
Classifier: Operating System :: OS Independent
Requires-Python: >=3.7
License-File: LICENSE
Requires-Dist: func_timeout>=4.3.5
Requires-Dist: httpx>=0.28.1
Requires-Dist: numpy>=1.24.0
Requires-Dist: sqlfluff>=3.3.1
Requires-Dist: sqlparse>=0.5.3
Requires-Dist: tqdm>=4.66.5
Provides-Extra: test
Requires-Dist: pytest>=7.0.0; extra == "test"
Requires-Dist: pytest-cov>=3.0.0; extra == "test"
Dynamic: license-file
